__init__.py
cli.py
version.py
devstack_cli-11.0.243.dist-info/licenses/LICENSE
devstack_cli-11.0.243.dist-info/METADATA
devstack_cli-11.0.243.dist-info/WHEEL
devstack_cli-11.0.243.dist-info/entry_points.txt
devstack_cli-11.0.243.dist-info/top_level.txt
devstack_cli-11.0.243.dist-info/RECORD
