Metadata-Version: 2.4
Name: devstack-cli
Version: 11.0.243
Summary: Command-line access to Cloud Development Environments (CDEs) created by Cloudomation DevStack
Author-email: Stefan Mückstein <stefan@cloudomation.com>
Project-URL: Homepage, https://cloudomation.com/
Project-URL: Documentation, https://docs.cloudomation.com/devstack/
Classifier: Programming Language :: Python :: 3
Classifier: License :: OSI Approved :: MIT License
Classifier: Operating System :: OS Independent
Requires-Python: >=3.8
License-File: LICENSE
Requires-Dist: paramiko
Requires-Dist: watchdog
Requires-Dist: rich
Requires-Dist: pyyaml
Requires-Dist: asyncssh
Requires-Dist: aiohttp
Requires-Dist: aiofiles
Requires-Dist: yarl
Dynamic: license-file
